<jua_overlay name="DoubleDoorOverlay" id="ba1821cc-3b25-42ed-996d-b9f77550c911">
  <overlayset>
    <overlay xOffset="0" yOffset="0" facing="Front" distance="Up Close" filename="DoubleDoorOverlay_close_front.png" />
    <waoverlayll xOffset="0" yOffset="0" facing="Front" distance="Near By" filename="DoubleDoorOverlay_near_front.png" />
    <overlay xOffset="0" yOffset="0" facing="Front" distance="Far Away" filename="DoubleDoorOverlay_far_front.png" />
    <overlay xOffset="0" yOffset="0" facing="Front" distance="Far Away Secondary" filename="DoubleDoorOverlay_far_front_secondary.png" />
    <overlay xOffset="0" yOffset="0" facing="Right" distance="Up Close" filename="DoubleDoorOverlay_close_right.png" />
    <overlay xOffset="0" yOffset="0" facing="Left" distance="Up Close" filename="DoubleDoorOverlay_close_left.png" />
    <overlay xOffset="0" yOffset="0" facing="Right" distance="Near By" filename="DoubleDoorOverlay_near_right.png" />
    <overlay xOffset="0" yOffset="0" facing="Left" distance="Near By" filename="DoubleDoorOverlay_near_left.png" />
    <overlay xOffset="0" yOffset="0" facing="Right" distance="Far Away" filename="DoubleDoorOverlay_far_right.png" />
    <overlay xOffset="0" yOffset="0" facing="Left" distance="Far Away" filename="DoubleDoorOverlay_far_left.png" />
  </overlayset>
</jua_overlay>